[{"Avatar":"","Username":"@all","Name":"All","LastTweetTime":1613910113,"LastUpdateTime":1613910199,"TweetsCount":1540,"Pages":77},{"Avatar":"https://i.loli.net/2021/01/08/gjTvq2ow8aztCsf.jpg","Username":"FCBarcelona","Name":"FC Barcelona","LastTweetTime":1613910113,"LastUpdateTime":1613910198,"TweetsCount":1430,"Pages":72},{"Avatar":"https://i.loli.net/2021/01/09/Y6VrqPd5CKiyvSh.jpg","Username":"funnyordie","Name":"Funny Or Die","LastTweetTime":1610754688,"LastUpdateTime":1613910199,"TweetsCount":110,"Pages":6}]