{"Avatar":"https://i.loli.net/2021/03/09/kKhPwyzdNOga4RI.jpg","Username":"FCBarcelona","Name":"FC Barcelona","LastTweetTime":1616835657,"LastUpdateTime":1616848204,"TweetsCount":2213,"Pages":111,"Profile":{"Avatar":"https://i.loli.net/2021/03/09/kKhPwyzdNOga4RI.jpg","Banner":"https://pbs.twimg.com/profile_banners/96951800/1611217712","Biography":"#ForçaBarça! Join us: @fcbarcelona_cat @fcbarcelona_es @fcbarcelona_br @fcbarcelona_jp @fcbarcelona_id @fcbarcelona_ara @fcbarcelona_fra @fcbarcelona_tr","Birthday":"","FollowersCount":36041093,"FollowingCount":3297,"FriendsCount":95,"IsPrivate":false,"IsVerified":true,"Joined":"2009-12-15T09:53:50Z","LikesCount":3297,"ListedCount":30628,"Location":"Get BarçaTV+ 👉","Name":"FC Barcelona","PinnedTweetIDs":[],"TweetsCount":115096,"URL":"https://twitter.com/FCBarcelona","UserID":"96951800","Username":"FCBarcelona","Website":"http://barca.link/ob4230r8AYl"},"Tweets":[{"Hashtags":["BarçaElche"],"HTML":"🟢 \u003ca href=\"https://twitter.com/AntoGriezmann\"\u003e@AntoGriezmann\u003c/a\u003e, \u003ca href=\"https://twitter.com/sergino_dest\"\u003e@sergino_dest\u003c/a\u003e, \u003ca href=\"https://twitter.com/clement_lenglet\"\u003e@clement_lenglet\u003c/a\u003e   \u003cbr\u003e🔴 \u003ca href=\"https://twitter.com/MartinBraith\"\u003e@MartinBraith\u003c/a\u003e, \u003ca href=\"https://twitter.com/JordiAlba\"\u003e@JordiAlba\u003c/a\u003e, \u003ca href=\"https://twitter.com/3gerardpique\"\u003e@3gerardpique\u003c/a\u003e   \u003cbr\u003e","ID":"1364660504258609154","IsQuoted":false,"IsPin":false,"IsReply":false,"IsRetweet":false,"Likes":1117,"PermanentURL":"https://twitter.com/FCBarcelona/status/1364660504258609154","Photos":["https://i.loli.net/2021/02/25/uXx1Cr3Ra8vKOkg.jpg"],"Replies":43,"Retweets":58,"Text":"🟢 @AntoGriezmann, @sergino_dest, @clement_lenglet   \n🔴 @MartinBraith, @JordiAlba, @3gerardpique   \n\n#BarçaElche https://t.co/QdC9ZWnBe7","TimeParsed":"2021-02-24T19:36:33Z","Timestamp":1614195393,"URLs":null,"UserID":"96951800","Username":"FCBarcelona","Videos":null},{"Hashtags":["BarçaElche"],"HTML":"✌️ \u003ca href=\"https://twitter.com/MartinBraith\"\u003e@MartinBraith\u003c/a\u003e with a two-assist game! 💪💪 \u003ca href=\"https://twitter.com/hashtag/BarçaElche\"\u003e#BarçaElche\u003c/a\u003e ","ID":"1364660062434840585","IsQuoted":false,"IsPin":false,"IsReply":false,"IsRetweet":false,"Likes":2269,"PermanentURL":"https://twitter.com/FCBarcelona/status/1364660062434840585","Photos":["https://i.loli.net/2021/02/25/DFL9EuJNmphv15n.jpg"],"Replies":62,"Retweets":140,"Text":"✌️ @MartinBraith with a two-assist game! 💪💪 #BarçaElche https://t.co/jKrlzWPbVY","TimeParsed":"2021-02-24T19:34:47Z","Timestamp":1614195287,"URLs":null,"UserID":"96951800","Username":"FCBarcelona","Videos":null},{"Hashtags":["BARÇAELCHE"],"HTML":"💥💥💥 BOOOOOOOOOOOOOOOOOM! \u003ca href=\"https://twitter.com/JordiAlba\"\u003e@JordiAlba\u003c/a\u003e VOLLEYS IN FROM CLOSE RANGE! 3-0! \u003ca href=\"https://twitter.com/hashtag/BARÇAELCHE\"\u003e#BARÇAELCHE\u003c/a\u003e ","ID":"1364659251084480516","IsQuoted":false,"IsPin":false,"IsReply":false,"IsRetweet":false,"Likes":1663,"PermanentURL":"https://twitter.com/FCBarcelona/status/1364659251084480516","Photos":["https://i.loli.net/2021/02/25/15vdrDhq69gSewK.jpg"],"Replies":58,"Retweets":196,"Text":"💥💥💥 BOOOOOOOOOOOOOOOOOM! @JordiAlba VOLLEYS IN FROM CLOSE RANGE! 3-0! #BARÇAELCHE https://t.co/rOYgPqYoBi","TimeParsed":"2021-02-24T19:31:34Z","Timestamp":1614195094,"URLs":null,"UserID":"96951800","Username":"FCBarcelona","Videos":[{"ID":"1364659230486261767","Preview":"https://i.loli.net/2021/02/25/15vdrDhq69gSewK.jpg","URL":"https://video.twimg.com/amplify_video/1364659230486261767/vid/480x480/vkIiqB7I_SXvh5C3.mp4?tag=13"}]},{"Hashtags":["MESSI","BARÇAELCHE"],"HTML":"💥💥 BOOOOOOOOOOM! LEO \u003ca href=\"https://twitter.com/hashtag/MESSI\"\u003e#MESSI\u003c/a\u003e DOES IT AGAIN! 2-0! \u003ca href=\"https://twitter.com/hashtag/BARÇAELCHE\"\u003e#BARÇAELCHE\u003c/a\u003e ","ID":"1364657978998198276","IsQuoted":false,"IsPin":false,"IsReply":false,"IsRetweet":false,"Likes":2896,"PermanentURL":"https://twitter.com/FCBarcelona/status/1364657978998198276","Photos":["https://i.loli.net/2021/02/25/JtqbUKXwA5vCyxT.jpg"],"Replies":121,"Retweets":387,"Text":"💥💥 BOOOOOOOOOOM! LEO #MESSI DOES IT AGAIN! 2-0! #BARÇAELCHE https://t.co/SZCOLnn91N","TimeParsed":"2021-02-24T19:26:30Z","Timestamp":1614194790,"URLs":null,"UserID":"96951800","Username":"FCBarcelona","Videos":[{"ID":"1364657959452749826","Preview":"https://i.loli.net/2021/02/25/JtqbUKXwA5vCyxT.jpg","URL":"https://video.twimg.com/amplify_video/1364657959452749826/vid/480x480/rj9q3LqCoZI9J3i0.mp4?tag=13"}]},{"Hashtags":["Messi"],"HTML":"Props to \u003ca href=\"https://twitter.com/MartinBraith\"\u003e@MartinBraith\u003c/a\u003e for the gorgeous 🅰️ on \u003ca href=\"https://twitter.com/hashtag/Messi's\"\u003e#Messi's\u003c/a\u003e goal! 👏👏👏 ","ID":"1364654449172615177","IsQuoted":false,"IsPin":false,"IsReply":false,"IsRetweet":false,"Likes":3253,"PermanentURL":"https://twitter.com/FCBarcelona/status/1364654449172615177","Photos":["https://i.loli.net/2021/02/25/Gcm6BeNYj9ZQVWx.jpg"],"Replies":60,"Retweets":159,"Text":"Props to @MartinBraith for the gorgeous 🅰️ on #Messi's goal! 👏👏👏 https://t.co/UyKsbCgCTT","TimeParsed":"2021-02-24T19:12:29Z","Timestamp":1614193949,"URLs":null,"UserID":"96951800","Username":"FCBarcelona","Videos":null},{"Hashtags":["MESSI","BARÇAELCHE"],"HTML":"💥 BOOM! LEO \u003ca href=\"https://twitter.com/hashtag/MESSI\"\u003e#MESSI\u003c/a\u003e GIVES BARÇA THE LEAD TO START THE SECOND HALF! 1-0! \u003ca href=\"https://twitter.com/hashtag/BARÇAELCHE\"\u003e#BARÇAELCHE\u003c/a\u003e ","ID":"1364652976632168449","IsQuoted":false,"IsPin":false,"IsReply":false,"IsRetweet":false,"Likes":2273,"PermanentURL":"https://twitter.com/FCBarcelona/status/1364652976632168449","Photos":["https://i.loli.net/2021/02/25/peOMXLtqdRxlh6D.jpg"],"Replies":101,"Retweets":342,"Text":"💥 BOOM! LEO #MESSI GIVES BARÇA THE LEAD TO START THE SECOND HALF! 1-0! #BARÇAELCHE https://t.co/UgqVvO0zTk","TimeParsed":"2021-02-24T19:06:38Z","Timestamp":1614193598,"URLs":null,"UserID":"96951800","Username":"FCBarcelona","Videos":[{"ID":"1364652958663798791","Preview":"https://i.loli.net/2021/02/25/peOMXLtqdRxlh6D.jpg","URL":"https://video.twimg.com/amplify_video/1364652958663798791/vid/720x720/4ETX9I75v795q-Y9.mp4?tag=13"}]},{"Hashtags":["BarçaElche"],"HTML":"🟢 \u003ca href=\"https://twitter.com/Dembouz\"\u003e@Dembouz\u003c/a\u003e \u003cbr\u003e🔴 \u003ca href=\"https://twitter.com/Miralem_Pjanic\"\u003e@Miralem_Pjanic\u003c/a\u003e \u003cbr\u003e","ID":"1364652188476338184","IsQuoted":false,"IsPin":false,"IsReply":false,"IsRetweet":false,"Likes":1117,"PermanentURL":"https://twitter.com/FCBarcelona/status/1364652188476338184","Photos":["https://i.loli.net/2021/02/25/58rBzXOxM4LNdcU.jpg"],"Replies":32,"Retweets":58,"Text":"🟢 @Dembouz \n🔴 @Miralem_Pjanic \n\n#BarçaElche https://t.co/jhN171zMTA","TimeParsed":"2021-02-24T19:03:30Z","Timestamp":1614193410,"URLs":null,"UserID":"96951800","Username":"FCBarcelona","Videos":null},{"Hashtags":["BarçaElche"],"HTML":"HALFTIME\u003cbr\u003e\u003cbr\u003e0️⃣ Barça\u003cbr\u003e0️⃣ Elche\u003cbr\u003e\u003cbr\u003eLive analysis: \u003ca href=\"http://barca.link/ykT030rhzBq\"\u003ehttps://t.co/bbVNGXoMPq\u003c/a\u003e\u003cbr\u003e","ID":"1364648620121878529","IsQuoted":false,"IsPin":false,"IsReply":false,"IsRetweet":false,"Likes":1150,"PermanentURL":"https://twitter.com/FCBarcelona/status/1364648620121878529","Photos":["https://i.loli.net/2021/02/25/VLQ3dazxBpoXOyC.jpg"],"Replies":192,"Retweets":81,"Text":"HALFTIME\n\n0️⃣ Barça\n0️⃣ Elche\n\nLive analysis: https://t.co/bbVNGXoMPq\n\n#BarçaElche https://t.co/qiQJl1sV1H","TimeParsed":"2021-02-24T18:49:19Z","Timestamp":1614192559,"URLs":["http://barca.link/ykT030rhzBq"],"UserID":"96951800","Username":"FCBarcelona","Videos":null},{"Hashtags":null,"HTML":"🤯 Trincão with a surreal combination of moves in the box but his point-blank shot is somehow saved!","ID":"1364641682344599555","IsQuoted":false,"IsPin":false,"IsReply":false,"IsRetweet":false,"Likes":2951,"PermanentURL":"https://twitter.com/FCBarcelona/status/1364641682344599555","Photos":null,"Replies":97,"Retweets":118,"Text":"🤯 Trincão with a surreal combination of moves in the box but his point-blank shot is somehow saved!","TimeParsed":"2021-02-24T18:21:45Z","Timestamp":1614190905,"URLs":null,"UserID":"96951800","Username":"FCBarcelona","Videos":null},{"Hashtags":["BarçaElche"],"HTML":"Trincão with an excellent chance right off the bat! \u003ca href=\"https://twitter.com/hashtag/BarçaElche\"\u003e#BarçaElche\u003c/a\u003e","ID":"1364637232397705216","IsQuoted":false,"IsPin":false,"IsReply":false,"IsRetweet":false,"Likes":1678,"PermanentURL":"https://twitter.com/FCBarcelona/status/1364637232397705216","Photos":null,"Replies":54,"Retweets":61,"Text":"Trincão with an excellent chance right off the bat! #BarçaElche","TimeParsed":"2021-02-24T18:04:04Z","Timestamp":1614189844,"URLs":null,"UserID":"96951800","Username":"FCBarcelona","Videos":null},{"Hashtags":["BarçaElche"],"HTML":"Aaaaaand the ball is rolling at Camp Nou!\u003cbr\u003e\u003ca href=\"https://twitter.com/hashtag/BarçaElche\"\u003e#BarçaElche\u003c/a\u003e\u003cbr\u003e💪🟦🟥","ID":"1364636439493885952","IsQuoted":false,"IsPin":false,"IsReply":false,"IsRetweet":false,"Likes":989,"PermanentURL":"https://twitter.com/FCBarcelona/status/1364636439493885952","Photos":null,"Replies":43,"Retweets":80,"Text":"Aaaaaand the ball is rolling at Camp Nou!\n#BarçaElche\n💪🟦🟥","TimeParsed":"2021-02-24T18:00:55Z","Timestamp":1614189655,"URLs":null,"UserID":"96951800","Username":"FCBarcelona","Videos":null},{"Hashtags":["BarçaElche"],"HTML":"Just about game time. 🔥 \u003ca href=\"https://twitter.com/hashtag/BarçaElche\"\u003e#BarçaElche\u003c/a\u003e ","ID":"1364634434234945540","IsQuoted":false,"IsPin":false,"IsReply":false,"IsRetweet":false,"Likes":1615,"PermanentURL":"https://twitter.com/FCBarcelona/status/1364634434234945540","Photos":["https://i.loli.net/2021/02/25/5ZqMnAtapwBUPKQ.jpg"],"Replies":58,"Retweets":112,"Text":"Just about game time. 🔥 #BarçaElche https://t.co/ckPhcZxPd6","TimeParsed":"2021-02-24T17:52:57Z","Timestamp":1614189177,"URLs":null,"UserID":"96951800","Username":"FCBarcelona","Videos":[{"ID":"1364634397769629701","Preview":"https://i.loli.net/2021/02/25/5ZqMnAtapwBUPKQ.jpg","URL":"https://video.twimg.com/amplify_video/1364634397769629701/vid/320x320/DEp2ds-oVTKcjkhG.mp4?tag=13"}]},{"Hashtags":["BarçaElche","ForçaBarça"],"HTML":"🟢🔴 Our subs for \u003ca href=\"https://twitter.com/hashtag/BarçaElche\"\u003e#BarçaElche\u003c/a\u003e:\u003cbr\u003e\u003cbr\u003e2 Dest\u003cbr\u003e5 Sergio\u003cbr\u003e7 Griezmann\u003cbr\u003e11 O Dembélé\u003cbr\u003e12 Riqui Puig\u003cbr\u003e13 Neto (GK)\u003cbr\u003e15 Lenglet\u003cbr\u003e19 Matheus\u003cbr\u003e24 Junior\u003cbr\u003e26 Iñaki Peña (GK)\u003cbr\u003e29 Konrad\u003cbr\u003e","ID":"1364631421835501574","IsQuoted":false,"IsPin":false,"IsReply":false,"IsRetweet":false,"Likes":1330,"PermanentURL":"https://twitter.com/FCBarcelona/status/1364631421835501574","Photos":["https://i.loli.net/2021/02/25/E4hGwtTnzv6c9uR.jpg"],"Replies":65,"Retweets":78,"Text":"🟢🔴 Our subs for #BarçaElche:\n\n2 Dest\n5 Sergio\n7 Griezmann\n11 O Dembélé\n12 Riqui Puig\n13 Neto (GK)\n15 Lenglet\n19 Matheus\n24 Junior\n26 Iñaki Peña (GK)\n29 Konrad\n\n#ForçaBarça 💪🔵🔴 https://t.co/7LJYkBeNbz","TimeParsed":"2021-02-24T17:40:59Z","Timestamp":1614188459,"URLs":null,"UserID":"96951800","Username":"FCBarcelona","Videos":null},{"Hashtags":["BarçaElche"],"HTML":"👋 Here for \u003ca href=\"https://twitter.com/hashtag/BarçaElche\"\u003e#BarçaElche\u003c/a\u003e 💪🟦🟥 ","ID":"1364629248229732367","IsQuoted":false,"IsPin":false,"IsReply":false,"IsRetweet":false,"Likes":1910,"PermanentURL":"https://twitter.com/FCBarcelona/status/1364629248229732367","Photos":["https://i.loli.net/2021/02/25/FMx3dpciOyhf5Cj.jpg"],"Replies":50,"Retweets":127,"Text":"👋 Here for #BarçaElche 💪🟦🟥 https://t.co/9gKeAvl91n","TimeParsed":"2021-02-24T17:32:21Z","Timestamp":1614187941,"URLs":null,"UserID":"96951800","Username":"FCBarcelona","Videos":[{"ID":"1364629201920393220","Preview":"https://i.loli.net/2021/02/25/FMx3dpciOyhf5Cj.jpg","URL":"https://video.twimg.com/amplify_video/1364629201920393220/vid/720x720/x6qInR6RvTHOBh5g.mp4?tag=13"}]},{"Hashtags":["BarçaElche"],"HTML":"Home again for a midweek clash.","ID":"1364626321536667650","IsQuoted":false,"IsPin":false,"IsReply":false,"IsRetweet":false,"Likes":1061,"PermanentURL":"https://twitter.com/FCBarcelona/status/1364626321536667650","Photos":["https://i.loli.net/2021/02/25/fwKnV824xYg6dEG.jpg"],"Replies":43,"Retweets":55,"Text":"Home again for a midweek clash.\n#BarçaElche 🔊 https://t.co/dl1Y3hEiML","TimeParsed":"2021-02-24T17:20:43Z","Timestamp":1614187243,"URLs":null,"UserID":"96951800","Username":"FCBarcelona","Videos":[{"ID":"1364626284077338628","Preview":"https://i.loli.net/2021/02/25/fwKnV824xYg6dEG.jpg","URL":"https://video.twimg.com/amplify_video/1364626284077338628/vid/480x480/ehUDRyKWPpdwUfEi.mp4?tag=13"}]},{"Hashtags":["BarçaElche"],"HTML":"🔵🔴  BARÇA LIVE \u003cbr\u003e⚽ \u003ca href=\"https://twitter.com/hashtag/BarçaElche\"\u003e#BarçaElche\u003c/a\u003e!\u003cbr\u003e🔥 Warm Up \u0026amp; Match Center \u003ca href=\"https://twitter.com/i/broadcasts/1vOxwEYZvLoGB\"\u003ehttps://t.co/5QUQzDWMkj\u003c/a\u003e","ID":"1364621446094458887","IsQuoted":false,"IsPin":false,"IsReply":false,"IsRetweet":false,"Likes":965,"PermanentURL":"https://twitter.com/FCBarcelona/status/1364621446094458887","Photos":null,"Replies":49,"Retweets":80,"Text":"🔵🔴  BARÇA LIVE \n⚽ #BarçaElche!\n🔥 Warm Up \u0026amp; Match Center https://t.co/5QUQzDWMkj","TimeParsed":"2021-02-24T17:01:20Z","Timestamp":1614186080,"URLs":["https://twitter.com/i/broadcasts/1vOxwEYZvLoGB"],"UserID":"96951800","Username":"FCBarcelona","Videos":null},{"Hashtags":["Culers","BarçaElche"],"HTML":"🙋‍♂️ \u003ca href=\"https://twitter.com/hashtag/Culers\"\u003e#Culers\u003c/a\u003e! Your starting XI for \u003ca href=\"https://twitter.com/hashtag/BarçaElche\"\u003e#BarçaElche\u003c/a\u003e! ","ID":"1364616460941877250","IsQuoted":false,"IsPin":false,"IsReply":false,"IsRetweet":false,"Likes":450,"PermanentURL":"https://twitter.com/FCBarcelona/status/1364616460941877250","Photos":["https://i.loli.net/2021/02/25/dMFTmG4kWgxVeo5.jpg"],"Replies":65,"Retweets":55,"Text":"🙋‍♂️ #Culers! Your starting XI for #BarçaElche! https://t.co/bFme7J9Xhy","TimeParsed":"2021-02-24T16:41:32Z","Timestamp":1614184892,"URLs":null,"UserID":"96951800","Username":"FCBarcelona","Videos":null},{"Hashtags":["BarçaElche"],"HTML":"💁‍♂️ Everything you need to know about \u003ca href=\"https://twitter.com/Elche_EN\"\u003e@Elche_EN\u003c/a\u003e\u003cbr\u003e\u003ca href=\"https://twitter.com/hashtag/BarçaElche\"\u003e#BarçaElche\u003c/a\u003e\u003cbr\u003e\u003ca href=\"http://barca.link/qRHt50DIa6w\"\u003ehttps://t.co/DVnKyPv9bw\u003c/a\u003e","ID":"1364591121083609096","IsQuoted":false,"IsPin":false,"IsReply":false,"IsRetweet":false,"Likes":884,"PermanentURL":"https://twitter.com/FCBarcelona/status/1364591121083609096","Photos":null,"Replies":35,"Retweets":43,"Text":"💁‍♂️ Everything you need to know about @Elche_EN\n#BarçaElche\nhttps://t.co/DVnKyPv9bw","TimeParsed":"2021-02-24T15:00:50Z","Timestamp":1614178850,"URLs":["http://barca.link/qRHt50DIa6w"],"UserID":"96951800","Username":"FCBarcelona","Videos":null},{"Hashtags":["BarçaElche"],"HTML":"🎙 \u003ca href=\"https://twitter.com/RonaldKoeman\"\u003e@RonaldKoeman\u003c/a\u003e says this moment in the season is ❛crucial.❜ \u003ca href=\"https://twitter.com/hashtag/BarçaElche\"\u003e#BarçaElche\u003c/a\u003e ","ID":"1364561051145101317","IsQuoted":false,"IsPin":false,"IsReply":false,"IsRetweet":false,"Likes":1559,"PermanentURL":"https://twitter.com/FCBarcelona/status/1364561051145101317","Photos":["https://i.loli.net/2021/02/25/njQbv3mLax1VYfH.jpg"],"Replies":77,"Retweets":78,"Text":"🎙 @RonaldKoeman says this moment in the season is ❛crucial.❜ #BarçaElche https://t.co/yQ93sfFewo","TimeParsed":"2021-02-24T13:01:21Z","Timestamp":1614171681,"URLs":null,"UserID":"96951800","Username":"FCBarcelona","Videos":[{"ID":"1364560926427463683","Preview":"https://i.loli.net/2021/02/25/njQbv3mLax1VYfH.jpg","URL":"https://video.twimg.com/amplify_video/1364560926427463683/vid/480x270/_KMD-nD0zSrJYjto.mp4?tag=13"}]},{"Hashtags":["BarçaElche"],"HTML":"👥 SQUAD LIST ⚽ \u003ca href=\"https://twitter.com/hashtag/BarçaElche\"\u003e#BarçaElche\u003c/a\u003e ","ID":"1364526874920165376","IsQuoted":false,"IsPin":false,"IsReply":false,"IsRetweet":false,"Likes":2495,"PermanentURL":"https://twitter.com/FCBarcelona/status/1364526874920165376","Photos":["https://i.loli.net/2021/02/24/ZxbtqhEvjA3Q9C1.jpg"],"Replies":116,"Retweets":179,"Text":"👥 SQUAD LIST ⚽ #BarçaElche https://t.co/F9sWvaFIqV","TimeParsed":"2021-02-24T10:45:33Z","Timestamp":1614163533,"URLs":null,"UserID":"96951800","Username":"FCBarcelona","Videos":null}]}