[{"Avatar":"","Username":"@all","Name":"All","LastTweetTime":1617364855,"LastUpdateTime":1617366664,"TweetsCount":2538,"Pages":127},{"Avatar":"https://i.loli.net/2021/03/09/kKhPwyzdNOga4RI.jpg","Username":"FCBarcelona","Name":"FC Barcelona","LastTweetTime":1617364855,"LastUpdateTime":1617366662,"TweetsCount":2299,"Pages":115},{"Avatar":"https://i.loli.net/2021/01/09/Y6VrqPd5CKiyvSh.jpg","Username":"funnyordie","Name":"Funny Or Die","LastTweetTime":1615167071,"LastUpdateTime":1617366664,"TweetsCount":239,"Pages":12}]