[{"Avatar":"","Username":"@all","Name":"All","LastTweetTime":1610500032,"LastUpdateTime":1610500670,"TweetsCount":537,"Pages":27},{"Avatar":"https://i.loli.net/2021/01/08/gjTvq2ow8aztCsf.jpg","Username":"FCBarcelona","Name":"FC Barcelona","LastTweetTime":1610499606,"LastUpdateTime":1610500658,"TweetsCount":438,"Pages":22},{"Avatar":"https://i.loli.net/2021/01/09/Y6VrqPd5CKiyvSh.jpg","Username":"funnyordie","Name":"Funny Or Die","LastTweetTime":1610500032,"LastUpdateTime":1610500670,"TweetsCount":99,"Pages":5}]